MANIFEST.in
README.md
setup.py
links_luxuryadmin_follit.egg-info/PKG-INFO
links_luxuryadmin_follit.egg-info/SOURCES.txt
links_luxuryadmin_follit.egg-info/dependency_links.txt
links_luxuryadmin_follit.egg-info/top_level.txt
luxuryadmin/__init__.py
luxuryadmin/admin.py
luxuryadmin/ajax.py
luxuryadmin/context_processors.py
luxuryadmin/forms.py
luxuryadmin/models.py
luxuryadmin/tests.py
luxuryadmin/urls.py
luxuryadmin/utils.py
luxuryadmin/views.py
luxuryadmin/jstemplates/categoryRow.html
luxuryadmin/jstemplates/pageRow.html
luxuryadmin/jstemplates/productImageRow.html
luxuryadmin/jstemplates/productRow.html
luxuryadmin/migrations/0001_initial.py
luxuryadmin/migrations/__init__.py
luxuryadmin/static/css/smoothness/jquery-ui-1.8.23.custom.css
luxuryadmin/static/css/smoothness/images/ui-bg_flat_0_aaaaaa_40x100.png
luxuryadmin/static/css/smoothness/images/ui-bg_flat_75_ffffff_40x100.png
luxuryadmin/static/css/smoothness/images/ui-bg_glass_55_fbf9ee_1x400.png
luxuryadmin/static/css/smoothness/images/ui-bg_glass_65_ffffff_1x400.png
luxuryadmin/static/css/smoothness/images/ui-bg_glass_75_dadada_1x400.png
luxuryadmin/static/css/smoothness/images/ui-bg_glass_75_e6e6e6_1x400.png
luxuryadmin/static/css/smoothness/images/ui-bg_glass_95_fef1ec_1x400.png
luxuryadmin/static/css/smoothness/images/ui-bg_highlight-soft_75_cccccc_1x100.png
luxuryadmin/static/css/smoothness/images/ui-icons_222222_256x240.png
luxuryadmin/static/css/smoothness/images/ui-icons_2e83ff_256x240.png
luxuryadmin/static/css/smoothness/images/ui-icons_454545_256x240.png
luxuryadmin/static/css/smoothness/images/ui-icons_888888_256x240.png
luxuryadmin/static/css/smoothness/images/ui-icons_cd0a0a_256x240.png
luxuryadmin/static/js/ICanHaz.min.js
luxuryadmin/static/js/csrf.js
luxuryadmin/static/js/form2js.js
luxuryadmin/static/js/jquery.ba-serializeobject.js
luxuryadmin/static/js/jquery.cookie.js
luxuryadmin/static/js/jquery.dajax.core.js
luxuryadmin/static/js/jquery.drag.drop.js
luxuryadmin/static/js/jquery.toObject.js
luxuryadmin/static/luxuryadmin/css/admin.css
luxuryadmin/static/luxuryadmin/js/categories.js
luxuryadmin/static/luxuryadmin/js/collection.js
luxuryadmin/static/luxuryadmin/js/lux.js
