Metadata-Version: 1.0
Name: links-luxuryadmin-follit
Version: 0.1.9
Summary: Luxury Admin for Django (follit fork)
Home-page: http://www.linkscreative.co.uk/
Author: James Cleveland
Author-email: jamescleveland@gmail.com
License: LICENSE.txt
Platform: UNKNOWN
